file_dealer/__init__.py
file_dealer/append.py
file_dealer/deleter.py
file_dealer/reader.py
file_dealer/writer.py
file_dealer-0.2.4.dist-info/METADATA
file_dealer-0.2.4.dist-info/WHEEL
file_dealer-0.2.4.dist-info/top_level.txt
file_dealer-0.2.4.dist-info/RECORD
