Metadata-Version: 2.4
Name: file_dealer
Version: 0.2.4
Summary: Helper functions to read, write, append and delete files easily.
Author-email: Ghena <ghenadiesturza@gmail.com>
License: MIT
Requires-Python: >=3.7
